flask_stathat
